GeneralisedFormanRicci/__init__.py
GeneralisedFormanRicci/frc.py
GeneralisedFormanRicci-0.3.dist-info/LICENSE
GeneralisedFormanRicci-0.3.dist-info/METADATA
GeneralisedFormanRicci-0.3.dist-info/WHEEL
GeneralisedFormanRicci-0.3.dist-info/top_level.txt
GeneralisedFormanRicci-0.3.dist-info/RECORD
