Metadata-Version: 2.1
Name: GeneralisedFormanRicci
Version: 0.3
Summary: A class to compute the Generalised Forman-Ricci curvature for a Simplicial Complex from a given point cloud data.
Home-page: https://github.com/ExpectozJJ/GeneralisedFormanRicci
Author: Wee JunJie
Author-email: expectozjj@gmail.com
License: UNKNOWN
Platform: UNKNOWN
Classifier: Programming Language :: Python :: 3
Classifier: License :: OSI Approved :: Apache Software License
Classifier: Operating System :: OS Independent
Requires-Python: >=3.6
